Metadata-Version: 2.1
Name: nonebot-plugin-buy
Version: 1.3
Summary: nonebot-plugin-buy
Author: QiYork
Author-email: 1309946582@qq.com
Project-URL: Homepage, https://github.com/Onimaimai/nonebot-plugin-buy
Classifier: Programming Language :: Python :: 3
Classifier: License :: OSI Approved :: MIT License
Classifier: Operating System :: OS Independent
Requires-Python: >=3.9
License-File: LICENSE
Requires-Dist: nonebot2
Requires-Dist: nonebot-adapter-onebot
Requires-Dist: nonebot-plugin-apscheduler
Requires-Dist: pydantic
